
[
    {
        "key": "datr",
        "value": "l-daaclvapQTi8iSe84VUbiy",
        "domain": "facebook.com",
        "path": "/",
        "hostOnly": false,
        "creation": "2026-01-04T22:32:48.504Z",
        "lastAccessed": "2026-01-04T22:32:48.504Z"
    },
    {
        "key": "sb",
        "value": "l-daaUEaJJqyvWf7g7_O13KK",
        "domain": "facebook.com",
        "path": "/",
        "hostOnly": false,
        "creation": "2026-01-04T22:32:48.504Z",
        "lastAccessed": "2026-01-04T22:32:48.504Z"
    },
    {
        "key": "dpr",
        "value": "2.25",
        "domain": "facebook.com",
        "path": "/",
        "hostOnly": false,
        "creation": "2026-01-04T22:32:48.504Z",
        "lastAccessed": "2026-01-04T22:32:48.504Z"
    },
    {
        "key": "c_user",
        "value": "61575291464706",
        "domain": "facebook.com",
        "path": "/",
        "hostOnly": false,
        "creation": "2026-01-04T22:32:48.504Z",
        "lastAccessed": "2026-01-04T22:32:48.505Z"
    },
    {
        "key": "wd",
        "value": "480x864",
        "domain": "facebook.com",
        "path": "/",
        "hostOnly": false,
        "creation": "2026-01-04T22:32:48.505Z",
        "lastAccessed": "2026-01-04T22:32:48.505Z"
    },
    {
        "key": "locale",
        "value": "en_GB",
        "domain": "facebook.com",
        "path": "/",
        "hostOnly": false,
        "creation": "2026-01-04T22:32:48.505Z",
        "lastAccessed": "2026-01-04T22:32:48.505Z"
    },
    {
        "key": "vpd",
        "value": "v1%3B576x320x2.25",
        "domain": "facebook.com",
        "path": "/",
        "hostOnly": false,
        "creation": "2026-01-04T22:32:48.505Z",
        "lastAccessed": "2026-01-04T22:32:48.505Z"
    },
    {
        "key": "xs",
        "value": "29%3AlxpeF3IFC4a5zw%3A2%3A1767565225%3A-1%3A-1%3A%3AAcydYJrgbuOgf5k7mPq5OC1D-yRrtd6uv84nhkn7Cg",
        "domain": "facebook.com",
        "path": "/",
        "hostOnly": false,
        "creation": "2026-01-04T22:32:48.505Z",
        "lastAccessed": "2026-01-04T22:32:48.505Z"
    },
    {
        "key": "fr",
        "value": "1Ez690NDRBbAot9VH.AWdJlRqjaYrc65wmcNmBMW5ffyebZjU4w1bnonVgaKEv1WYbFr0.BpWupC..AAA.0.0.BpWuqM.AWey5KsQzeR92CEI7rStHbSFung",
        "domain": "facebook.com",
        "path": "/",
        "hostOnly": false,
        "creation": "2026-01-04T22:32:48.505Z",
        "lastAccessed": "2026-01-04T22:32:48.505Z"
    },
    {
        "key": "fbl_st",
        "value": "100738132%3BT%3A29459432",
        "domain": "facebook.com",
        "path": "/",
        "hostOnly": false,
        "creation": "2026-01-04T22:32:48.505Z",
        "lastAccessed": "2026-01-04T22:32:48.505Z"
    },
    {
        "key": "wl_cbv",
        "value": "v2%3Bclient_version%3A3041%3Btimestamp%3A1767565964",
        "domain": "facebook.com",
        "path": "/",
        "hostOnly": false,
        "creation": "2026-01-04T22:32:48.505Z",
        "lastAccessed": "2026-01-04T22:32:48.505Z"
    }
        ]
